LICENSE
leetit/__init__.py
leetit/leetit/__init__.py
leetit/leetit/leetit.py
leetit/tests/test_leetit.py
leetit/tests/test_regexp.py
leetit-313.3.73.dist-info/LICENSE
leetit-313.3.73.dist-info/WHEEL
leetit-313.3.73.dist-info/METADATA
leetit-313.3.73.dist-info/RECORD
